hambster_test-0.2.dist-info/DESCRIPTION.rst
hambster_test-0.2.dist-info/METADATA
hambster_test-0.2.dist-info/RECORD
hambster_test-0.2.dist-info/WHEEL
hambster_test-0.2.dist-info/entry_points.txt
hambster_test-0.2.dist-info/metadata.json
hambster_test-0.2.dist-info/top_level.txt
runrun/__init__.py
wayne/__init__.py
wayne/circle.py
