Metadata-Version: 2.0
Name: hambster-test
Version: 0.2
Summary: A test Python project
Home-page: https://github.com/hambster/testproject
Author: hambster
Author-email: hambster@gmail.com
License: MIT
Keywords: test setuptools development
Platform: UNKNOWN
Classifier: Development Status :: 3 - Alpha
Classifier: Intended Audience :: Developers
Classifier: Topic :: Software Development :: Build Tools
Classifier: License :: OSI Approved :: MIT License
Classifier: Programming Language :: Python :: 2
Classifier: Programming Language :: Python :: 2.7
Requires-Dist: requests
